[
 {
  "set_start_frame": 0,
  "core_end_frame": 396,
  "attacked_basket": "left",
  "offense_team": 0,
  "confidence": 0.9,
  "offense_real": "CLE",
  "defense_real": "GSW",
  "status": "aligned",
  "period": 3,
  "anchors": [
   {
    "frame": 0,
    "period": 3,
    "clock_s": 211,
    "raw": "3ro|3:31"
   },
   {
    "frame": 396,
    "period": 3,
    "clock_s": 198,
    "raw": "3rn|3:18"
   }
  ],
  "pbp_possession": {
   "team": "home",
   "clock": [
    217.0,
    198.0
   ],
   "points": 2
  },
  "overlap_frac_of_span": 1.0,
  "offense_points": 2,
  "terminating_event": {
   "clock_s": 217.0,
   "team": "home",
   "kind": "ft_made",
   "desc": "H. Barnes makes free throw 2 of 2"
  },
  "pbp_offense_real": "GSW",
  "offense_agrees": false,
  "orientation_flipped": false,
  "offense_source": "orientation",
  "orientation_conf": 0.79
 },
 {
  "set_start_frame": 3684,
  "core_end_frame": 3861,
  "attacked_basket": "right",
  "offense_team": 1,
  "confidence": 0.78,
  "offense_real": "GSW",
  "defense_real": "CLE",
  "status": "no_pbp_overlap"
 },
 {
  "set_start_frame": 4710,
  "core_end_frame": 4872,
  "attacked_basket": "left",
  "offense_team": 0,
  "confidence": 1.0,
  "offense_real": "CLE",
  "defense_real": "GSW",
  "status": "aligned",
  "period": 3,
  "anchors": [
   {
    "frame": 4710,
    "period": 3,
    "clock_s": 172,
    "raw": "3ro|2:52"
   },
   {
    "frame": 4872,
    "period": 3,
    "clock_s": 166,
    "raw": "3ro|2:46"
   }
  ],
  "pbp_possession": {
   "team": "away",
   "clock": [
    183.0,
    162.0
   ],
   "points": 1
  },
  "overlap_frac_of_span": 1.0,
  "offense_points": 1,
  "terminating_event": {
   "clock_s": 162.0,
   "team": "away",
   "kind": "ft_missed",
   "desc": "T. Thompson misses free throw 2 of 2"
  },
  "pbp_offense_real": "CLE",
  "offense_agrees": true,
  "orientation_flipped": false,
  "offense_source": "orientation",
  "orientation_conf": 0.79
 },
 {
  "set_start_frame": 10407,
  "core_end_frame": 10668,
  "attacked_basket": "left",
  "offense_team": 0,
  "confidence": 0.89,
  "offense_real": "CLE",
  "defense_real": "GSW",
  "status": "aligned",
  "period": 3,
  "anchors": [
   {
    "frame": 10407,
    "period": 3,
    "clock_s": 108,
    "raw": "3rn|1:48"
   },
   {
    "frame": 10668,
    "period": 3,
    "clock_s": 99,
    "raw": "3Ro|1:39"
   }
  ],
  "pbp_possession": {
   "team": "away",
   "clock": [
    116.0,
    96.0
   ],
   "points": 2
  },
  "overlap_frac_of_span": 1.0,
  "offense_points": 2,
  "terminating_event": {
   "clock_s": 96.0,
   "team": "away",
   "kind": "shot_made",
   "desc": "L. James makes 2-pt jump shot from 12 ft"
  },
  "pbp_offense_real": "CLE",
  "offense_agrees": true,
  "orientation_flipped": false,
  "offense_source": "orientation",
  "orientation_conf": 0.79
 },
 {
  "set_start_frame": 11556,
  "core_end_frame": 11919,
  "attacked_basket": "left",
  "offense_team": 0,
  "confidence": 0.76,
  "offense_real": "CLE",
  "defense_real": "GSW",
  "status": "aligned",
  "period": 3,
  "anchors": [
   {
    "frame": 11556,
    "period": 3,
    "clock_s": 68,
    "raw": "3rn|1:08"
   },
   {
    "frame": 11737,
    "period": 3,
    "clock_s": 62,
    "raw": "3rn|1:02"
   }
  ],
  "pbp_possession": {
   "team": "away",
   "clock": [
    79.0,
    54.0
   ],
   "points": 2
  },
  "overlap_frac_of_span": 1.0,
  "offense_points": 2,
  "terminating_event": {
   "clock_s": 54.0,
   "team": "away",
   "kind": "shot_made",
   "desc": "T. Thompson makes 2-pt hook shot from 5 ft (assist by L. James )"
  },
  "pbp_offense_real": "CLE",
  "offense_agrees": true,
  "orientation_flipped": true,
  "offense_source": "orientation",
  "orientation_conf": 0.79
 },
 {
  "set_start_frame": 13053,
  "core_end_frame": 13224,
  "attacked_basket": "left",
  "offense_team": 0,
  "confidence": 0.71,
  "offense_real": "CLE",
  "defense_real": "GSW",
  "status": "anchor_inconsistent",
  "anchors": [
   {
    "frame": 13053,
    "period": 3,
    "clock_s": 122,
    "raw": "3rn|202"
   },
   {
    "frame": 13224,
    "period": 3,
    "clock_s": 101,
    "raw": "3ro|141"
   }
  ]
 },
 {
  "set_start_frame": 16458,
  "core_end_frame": 16578,
  "attacked_basket": "right",
  "offense_team": 1,
  "confidence": 0.54,
  "offense_real": "GSW",
  "defense_real": "CLE",
  "status": "aligned",
  "period": 4,
  "anchors": [
   {
    "frame": 16458,
    "period": 4,
    "clock_s": 679,
    "raw": "4th|11:19"
   },
   {
    "frame": 16578,
    "period": 4,
    "clock_s": 674,
    "raw": "4H|11:14"
   }
  ],
  "pbp_possession": {
   "team": "home",
   "clock": [
    694.0,
    674.0
   ],
   "points": 0
  },
  "overlap_frac_of_span": 1.0,
  "offense_points": 0,
  "terminating_event": {
   "clock_s": 674.0,
   "team": "home",
   "kind": "shot_missed",
   "desc": "S. Livingston misses 2-pt jump shot from 13 ft"
  },
  "pbp_offense_real": "GSW",
  "offense_agrees": true,
  "orientation_flipped": true,
  "offense_source": "orientation",
  "orientation_conf": 0.79
 }
]