{
  "frame": "clip_10m00_18m00__f001755.jpg",
  "image_path": "/Users/lucienmcnulty/Documents/Data Science projects/NBA Comp Viz New Project Version 3/data/visibility/truth/live/clip_10m00_18m00__f001755.jpg",
  "width": 1280,
  "height": 720,
  "boxes": [
    [
      133,
      206,
      205,
      308
    ],
    [
      175,
      256,
      253,
      376
    ],
    [
      316,
      255,
      360,
      386
    ],
    [
      337,
      185,
      391,
      303
    ],
    [
      395,
      254,
      499,
      378
    ],
    [
      641,
      394,
      718,
      562
    ],
    [
      556,
      166,
      631,
      318
    ],
    [
      560,
      180,
      615,
      300
    ],
    [
      600,
      217,
      678,
      406
    ],
    [
      649,
      321,
      698,
      414
    ]
  ]
}